django_cohort_analysis
