Metadata-Version: 1.1
Name: django-cohort-analysis
Version: 0.0.1
Summary: A small app to perform cohort analysis in Django
Home-page: https://github.com/jturner/django_cohort_analysis
Author: John Turner
Author-email: john@springmoves.com
License: BSD
Keywords: django,cohort,cohort analysis
Platform: UNKNOWN
Classifier: Development Status :: 2 - Pre-Alpha
Classifier: Intended Audience :: Developers
Classifier: License :: OSI Approved :: BSD License
Classifier: Natural Language :: English
Classifier: Programming Language :: Python :: 2
Classifier: Programming Language :: Python :: 2.6
Classifier: Programming Language :: Python :: 2.7
Classifier: Programming Language :: Python :: 3
Classifier: Programming Language :: Python :: 3.3
Classifier: Programming Language :: Python :: 3.4
